wbib/__init__.py
wbib/queries.py
wbib/render.py
wbib/wbib.py
wbib/templates/template.html.jinja
wbib-0.3.12.dist-info/LICENSE
wbib-0.3.12.dist-info/METADATA
wbib-0.3.12.dist-info/WHEEL
wbib-0.3.12.dist-info/top_level.txt
wbib-0.3.12.dist-info/RECORD
