Metadata-Version: 2.1
Name: wbib
Version: 0.3.12
Summary: A helper for building Wikidata-based literature dashboards via SPARQL queries. 
Home-page: https://github.com/lubianat/wbib
Author: Tiago Lubiana
Author-email: tiago.lubiana.alves@usp.br
License: MIT license
Keywords: wbib
Platform: UNKNOWN
Classifier: Development Status :: 2 - Pre-Alpha
Classifier: Intended Audience :: Developers
Classifier: License :: OSI Approved :: MIT License
Classifier: Natural Language :: English
Classifier: Programming Language :: Python :: 3
Classifier: Programming Language :: Python :: 3.5
Classifier: Programming Language :: Python :: 3.6
Classifier: Programming Language :: Python :: 3.7
Classifier: Programming Language :: Python :: 3.8
Requires-Python: >=3.5
License-File: LICENSE
Requires-Dist: pandas
Requires-Dist: wikidata2df
Requires-Dist: Jinja2
